.gitignore
LICENSE.md
README.md
setup.cfg
setup.py
djangocms_googlecalendar_plugin/__init__.py
djangocms_googlecalendar_plugin/cms_plugins.py
djangocms_googlecalendar_plugin/models.py
djangocms_googlecalendar_plugin.egg-info/PKG-INFO
djangocms_googlecalendar_plugin.egg-info/SOURCES.txt
djangocms_googlecalendar_plugin.egg-info/dependency_links.txt
djangocms_googlecalendar_plugin.egg-info/not-zip-safe
djangocms_googlecalendar_plugin.egg-info/requires.txt
djangocms_googlecalendar_plugin.egg-info/top_level.txt
djangocms_googlecalendar_plugin/migrations/0001_initial.py
djangocms_googlecalendar_plugin/migrations/0002_auto_20171117_1901.py
djangocms_googlecalendar_plugin/migrations/__init__.py
djangocms_googlecalendar_plugin/static/djangocms_googlecalendar/fullcalendar-3.4.0/CHANGELOG.txt
djangocms_googlecalendar_plugin/static/djangocms_googlecalendar/fullcalendar-3.4.0/CONTRIBUTING.txt
djangocms_googlecalendar_plugin/static/djangocms_googlecalendar/fullcalendar-3.4.0/LICENSE.txt
djangocms_googlecalendar_plugin/static/djangocms_googlecalendar/fullcalendar-3.4.0/fullcalendar.css
djangocms_googlecalendar_plugin/static/djangocms_googlecalendar/fullcalendar-3.4.0/fullcalendar.js
djangocms_googlecalendar_plugin/static/djangocms_googlecalendar/fullcalendar-3.4.0/fullcalendar.min.css
djangocms_googlecalendar_plugin/static/djangocms_googlecalendar/fullcalendar-3.4.0/fullcalendar.min.js
djangocms_googlecalendar_plugin/static/djangocms_googlecalendar/fullcalendar-3.4.0/fullcalendar.print.css
djangocms_googlecalendar_plugin/static/djangocms_googlecalendar/fullcalendar-3.4.0/fullcalendar.print.min.css
djangocms_googlecalendar_plugin/static/djangocms_googlecalendar/fullcalendar-3.4.0/gcal.js
djangocms_googlecalendar_plugin/static/djangocms_googlecalendar/fullcalendar-3.4.0/gcal.min.js
djangocms_googlecalendar_plugin/static/djangocms_googlecalendar/fullcalendar-3.4.0/locale-all.js
djangocms_googlecalendar_plugin/static/djangocms_googlecalendar/fullcalendar-3.4.0/demos/agenda-views.html
djangocms_googlecalendar_plugin/static/djangocms_googlecalendar/fullcalendar-3.4.0/demos/background-events.html
djangocms_googlecalendar_plugin/static/djangocms_googlecalendar/fullcalendar-3.4.0/demos/basic-views.html
djangocms_googlecalendar_plugin/static/djangocms_googlecalendar/fullcalendar-3.4.0/demos/default.html
